<?xml version="1.0" encoding="utf-8"?>
<SoundBanksInfo Platform="Mac" BasePlatform="Mac" SchemaVersion="16" SoundBankVersion="150">
	<RootPaths>
		<ProjectRoot>../..</ProjectRoot>
		<SourceFilesRoot>../../.cache/Mac</SourceFilesRoot>
		<SoundBanksRoot>.</SoundBanksRoot>
		<ExternalSourcesInputFile></ExternalSourcesInputFile>
		<ExternalSourcesOutputRoot>.</ExternalSourcesOutputRoot>
	</RootPaths>
	<DialogueEvents/>
	<SoundBanks>
		<SoundBank Id="1355168291" Type="User" Language="SFX" Hash="{52CE015E-9218-F6CD-E8EE-65F673AB5740}">
			<ShortName>Init</ShortName>
			<Path>Init.bnk</Path>
			<Plugins>
				<AudioDevices>
					<Plugin Id="2317455096" Name="No_Output" LibName="No Output" LibId="11862023"/>
					<Plugin Id="3859886410" Name="System" LibName="System" LibId="11403271"/>
				</AudioDevices>
			</Plugins>
			<Busses>
				<Bus Id="3803692087" Name="Master Audio Bus"/>
			</Busses>
		</SoundBank>
		<SoundBank Id="3161908922" Type="User" Language="SFX" Hash="{9C276364-9CE4-275A-4586-96733A51BCED}">
			<ShortName>Main</ShortName>
			<Path>Main.bnk</Path>
		</SoundBank>
		<SoundBank Id="4072029455" Type="User" Language="SFX" Hash="{ED2A68C9-1B35-A44F-E947-061DF543F286}">
			<ShortName>New_SoundBank</ShortName>
			<Path>New_SoundBank.bnk</Path>
			<Media>
				<File Id="184367809" Language="SFX" Streaming="false" Location="Memory">
					<ShortName>emotional-guitar-loop-02-301396.wav</ShortName>
					<CachePath>SFX/emotional-guitar-loop-02-301396_FBC78EF0.wem</CachePath>
				</File>
			</Media>
			<Plugins>
				<Custom>
					<Plugin Id="198026755" Name="Steam Audio Spatializer (Custom)" LibName="Steam Audio Spatializer" LibId="1987253171"/>
				</Custom>
			</Plugins>
			<Events>
				<Event Id="2879116096" Name="Play_emotional_guitar_loop_02_301396" MaxAttenuation="200" DurationType="Infinite">
					<MediaRefs>
						<MediaRef Id="184367809"/>
					</MediaRefs>
					<PluginRefs>
						<Custom>
							<PluginRef Id="198026755"/>
						</Custom>
					</PluginRefs>
				</Event>
			</Events>
		</SoundBank>
	</SoundBanks>
	<FileHash>{F09E118E-F5EA-3E4B-54D8-168E40B8D17C}</FileHash>
</SoundBanksInfo>
